[
  {
    "name": "81 St & N T 4.gpx",
    "start": [
      -73.962107,
      40.788892
    ],
    "end": [
      -73.961334,
      40.789185
    ],
    "backend": "osrm-foot/bike",
    "routeLenFt": 244.30234329487783,
    "beaconCount": 4,
    "driftFt": 2.316368196959042,
    "angleDeg": 6,
    "maxChordFt": 120,
    "minSpacingFt": null,
    "beacons": [
      [
        -73.962108,
        40.788893
      ],
      [
        -73.9619452603302,
        40.789000464628295
      ],
      [
        -73.96162795067472,
        40.78913135894846
      ],
      [
        -73.961337,
        40.789199
      ]
    ]
  },
  {
    "name": "81 St & N T 5.gpx",
    "start": [
      -73.962107,
      40.788892
    ],
    "end": [
      -73.961527,
      40.789153
    ],
    "backend": "osrm-foot/bike",
    "routeLenFt": 188.88723833856017,
    "beaconCount": 3,
    "driftFt": 3.71890973487459,
    "angleDeg": 8,
    "maxChordFt": 120,
    "minSpacingFt": null,
    "beacons": [
      [
        -73.962108,
        40.788893
      ],
      [
        -73.96188461068043,
        40.78903031174858
      ],
      [
        -73.961529,
        40.789157
      ]
    ]
  },
  {
    "name": "81 St & N T1.gpx",
    "start": [
      -73.962429,
      40.7912
    ],
    "end": [
      -73.961957,
      40.79102
    ],
    "backend": "osrm-foot/bike",
    "routeLenFt": 153.78482951923314,
    "beaconCount": 3,
    "driftFt": 2.957495290745413,
    "angleDeg": 1,
    "maxChordFt": 60,
    "minSpacingFt": 50,
    "beacons": [
      [
        -73.962425,
        40.791221
      ],
      [
        -73.96221316991051,
        40.79118680933886
      ],
      [
        -73.961933,
        40.791043
      ]
    ]
  },
  {
    "name": "81 St & N T2.gpx",
    "start": [
      -73.964574,
      40.791533
    ],
    "end": [
      -73.964338,
      40.791346
    ],
    "backend": "osrm-foot/bike",
    "routeLenFt": 99.42840745663615,
    "beaconCount": 3,
    "driftFt": 0.4812962938639642,
    "angleDeg": 1,
    "maxChordFt": 60,
    "minSpacingFt": null,
    "beacons": [
      [
        -73.964564,
        40.791543
      ],
      [
        -73.96438947757416,
        40.79144524538489
      ],
      [
        -73.964325,
        40.791349
      ]
    ]
  },
  {
    "name": "81 St & N T3.gpx",
    "start": [
      -73.963888,
      40.789411
    ],
    "end": [
      -73.963866,
      40.789837
    ],
    "backend": "osrm-foot/bike",
    "routeLenFt": 180.44893748866627,
    "beaconCount": 3,
    "driftFt": 3.653447842496339,
    "angleDeg": 6,
    "maxChordFt": 200,
    "minSpacingFt": null,
    "beacons": [
      [
        -73.963891,
        40.789394
      ],
      [
        -73.96383064477745,
        40.78939811737907
      ],
      [
        -73.963874,
        40.789836
      ]
    ]
  },
  {
    "name": "97 St & N T1.gpx",
    "start": [
      -73.962278,
      40.791784
    ],
    "end": [
      -73.961806,
      40.792191
    ],
    "backend": "osrm-foot/bike",
    "routeLenFt": 224.2296372263863,
    "beaconCount": 5,
    "driftFt": 3.779777108611383,
    "angleDeg": 3,
    "maxChordFt": 90,
    "minSpacingFt": 30,
    "beacons": [
      [
        -73.962276,
        40.791783
      ],
      [
        -73.96220247566738,
        40.791876359496804
      ],
      [
        -73.96214287967496,
        40.79208819592004
      ],
      [
        -73.96203245082039,
        40.79215747289458
      ],
      [
        -73.961815,
        40.792218
      ]
    ]
  },
  {
    "name": "97 St & N T2.gpx",
    "start": [
      -73.961377,
      40.795928
    ],
    "end": [
      -73.960669,
      40.796286
    ],
    "backend": "osrm-foot/bike",
    "routeLenFt": 10302.95204999175,
    "beaconCount": 147,
    "driftFt": 3.0089714445824587,
    "angleDeg": 1,
    "maxChordFt": 800,
    "minSpacingFt": null,
    "beacons": [
      [
        -73.961371,
        40.795925
      ],
      [
        -73.96077889807768,
        40.79674210264774
      ],
      [
        -73.96073261266338,
        40.796761378308865
      ],
      [
        -73.96069757922176,
        40.79680935889193
      ],
      [
        -73.96070132873491,
        40.79684864917814
      ],
      [
        -73.95930826247508,
        40.79877132821627
      ],
      [
        -73.95891491942966,
        40.79929552190344
      ],
      [
        -73.95872694836922,
        40.7995297836134
      ],
      [
        -73.9582684087748,
        40.80015223458122
      ],
      [
        -73.95821546972957,
        40.800187738280165
      ],
      [
        -73.95814488943955,
        40.80019905009039
      ],
      [
        -73.95807327863899,
        40.800207082441254
      ],
      [
        -73.95800357598056,
        40.800220885772866
      ],
      [
        -73.95786770355402,
        40.800258486167245
      ],
      [
        -73.95774204625936,
        40.80031198972014
      ],
      [
        -73.95767318722628,
        40.8003006011704
      ],
      [
        -73.95513666519352,
        40.79924143050865
      ],
      [
        -73.95260609888852,
        40.79817416191817
      ],
      [
        -73.95007599340488,
        40.79710633764768
      ],
      [
        -73.94982189597938,
        40.797001045691246
      ],
      [
        -73.94976326088778,
        40.796971269598004
      ],
      [
        -73.94977238853669,
        40.7969192229266
      ],
      [
        -73.94979368033482,
        40.79686683112947
      ],
      [
        -73.94980148114445,
        40.79681265149991
      ],
      [
        -73.94978569919755,
        40.79675992024502
      ],
      [
        -73.94975613925698,
        40.796710139256966
      ],
      [
        -73.94970713634822,
        40.796669954534444
      ],
      [
        -73.94964598822362,
        40.79664090027567
      ],
      [
        -73.94960693743455,
        40.796595874869105
      ],
      [
        -73.95100436924356,
        40.794675892256954
      ],
      [
        -73.95240167505798,
        40.792755097614645
      ],
      [
        -73.95310225988156,
        40.791795493941365
      ],
      [
        -73.95307650674162,
        40.79177925850529
      ],
      [
        -73.95304438489786,
        40.7918261606503
      ],
      [
        -73.95322519820589,
        40.79191717329538
      ],
      [
        -73.95345699208809,
        40.79204851398695
      ],
      [
        -73.9535029747449,
        40.7920906157981
      ],
      [
        -73.95357239377331,
        40.792186791166785
      ],
      [
        -73.95378293609718,
        40.79253334676196
      ],
      [
        -73.95383832730211,
        40.79256865865509
      ],
      [
        -73.95394573248832,
        40.792642179102444
      ],
      [
        -73.9541302993663,
        40.792728730066905
      ],
      [
        -73.95418846048534,
        40.79276134641765
      ],
      [
        -73.95424500014717,
        40.792795545554895
      ],
      [
        -73.95429463597951,
        40.79283516845618
      ],
      [
        -73.95437815660969,
        40.79292468234138
      ],
      [
        -73.95444474354926,
        40.7930220426644
      ],
      [
        -73.95447356355012,
        40.79307233639141
      ],
      [
        -73.95451505658862,
        40.7931075567034
      ],
      [
        -73.95473222773806,
        40.793104535863755
      ],
      [
        -73.95480439958429,
        40.7931078827192
      ],
      [
        -73.954876252023,
        40.79311469631252
      ],
      [
        -73.95501789922324,
        40.79313707493527
      ],
      [
        -73.95504827799013,
        40.79316785985827
      ],
      [
        -73.95506382923239,
        40.793216325249375
      ],
      [
        -73.95516046068192,
        40.79329796255421
      ],
      [
        -73.9552166945265,
        40.793331354767595
      ],
      [
        -73.95535491574829,
        40.793363762151586
      ],
      [
        -73.95542065486427,
        40.79335779016842
      ],
      [
        -73.95548992284684,
        40.79334295215922
      ],
      [
        -73.9555609973366,
        40.79333272143555
      ],
      [
        -73.95563271493953,
        40.79332513591986
      ],
      [
        -73.95577744739747,
        40.793321315176804
      ],
      [
        -73.95592196140954,
        40.79332775857922
      ],
      [
        -73.95621083628949,
        40.793343244177976
      ],
      [
        -73.95628324557215,
        40.79334387934712
      ],
      [
        -73.95635560445437,
        40.793342088985185
      ],
      [
        -73.95642744283238,
        40.79333608289353
      ],
      [
        -73.95649833186054,
        40.79332518548909
      ],
      [
        -73.95656755173506,
        40.793309193881306
      ],
      [
        -73.95663465067402,
        40.793288666942864
      ],
      [
        -73.95669705417681,
        40.79326125350611
      ],
      [
        -73.9567555862526,
        40.79322927582628
      ],
      [
        -73.9570062454859,
        40.7930315678302
      ],
      [
        -73.95706347191619,
        40.792998411233526
      ],
      [
        -73.95712797707424,
        40.79297356065017
      ],
      [
        -73.95719745940431,
        40.792958120132376
      ],
      [
        -73.95726875462857,
        40.79296732943178
      ],
      [
        -73.95733900179881,
        40.79297981779495
      ],
      [
        -73.95738813580384,
        40.793020084176405
      ],
      [
        -73.957478132482,
        40.79310599009644
      ],
      [
        -73.95753887610297,
        40.79312109769583
      ],
      [
        -73.9576110053523,
        40.79311774743404
      ],
      [
        -73.957683211499,
        40.793121897212586
      ],
      [
        -73.9577499391379,
        40.793143009721085
      ],
      [
        -73.9578143232705,
        40.79316777065903
      ],
      [
        -73.95787594065551,
        40.79319657008898
      ],
      [
        -73.95821415486236,
        40.79329317682636
      ],
      [
        -73.95835642674486,
        40.79331334704415
      ],
      [
        -73.95842870330962,
        40.79331672445372
      ],
      [
        -73.95857344101222,
        40.79331738833245
      ],
      [
        -73.95893403794757,
        40.793294887657304
      ],
      [
        -73.95907871952113,
        40.79329981998368
      ],
      [
        -73.95922146241087,
        40.79331810623617
      ],
      [
        -73.9593628105121,
        40.79334188138633
      ],
      [
        -73.95950325091171,
        40.793368666411
      ],
      [
        -73.95950644448384,
        40.79342244590172
      ],
      [
        -73.9595195844055,
        40.793475913060554
      ],
      [
        -73.95957988536826,
        40.793633881672804
      ],
      [
        -73.95959686902012,
        40.79368717520109
      ],
      [
        -73.959773,
        40.79416131067059
      ],
      [
        -73.95976962829862,
        40.79421597084669
      ],
      [
        -73.95976044721826,
        40.79427035109187
      ],
      [
        -73.95973284959621,
        40.79437798156134
      ],
      [
        -73.95972904106817,
        40.7944325338862
      ],
      [
        -73.95973855752156,
        40.79448683677205
      ],
      [
        -73.95975894990775,
        40.79453878756919
      ],
      [
        -73.95965716254833,
        40.79461675933531
      ],
      [
        -73.95962045683126,
        40.79466381475311
      ],
      [
        -73.95959824435079,
        40.794715452445026
      ],
      [
        -73.95961362017805,
        40.79476770486192
      ],
      [
        -73.95967662488823,
        40.794866422904974
      ],
      [
        -73.95972789098403,
        40.79490093050884
      ],
      [
        -73.95985734458338,
        40.79495008482053
      ],
      [
        -73.95992626120817,
        40.794966913116035
      ],
      [
        -73.9599976155487,
        40.794974
      ],
      [
        -73.96014242992982,
        40.79497340338132
      ],
      [
        -73.96021417599782,
        40.794978890352596
      ],
      [
        -73.9602829165857,
        40.79499573097142
      ],
      [
        -73.96034964020166,
        40.79501701844378
      ],
      [
        -73.96041761770798,
        40.79503584676526
      ],
      [
        -73.9604886096638,
        40.79504622428736
      ],
      [
        -73.96056083005006,
        40.795049511528475
      ],
      [
        -73.96063323268011,
        40.79505056413152
      ],
      [
        -73.9607053578464,
        40.79505477024751
      ],
      [
        -73.96077180029884,
        40.79507614850278
      ],
      [
        -73.96083079725364,
        40.795107904388004
      ],
      [
        -73.96088292238605,
        40.79514577502917
      ],
      [
        -73.96092935152325,
        40.7951867932894
      ],
      [
        -73.96094952929639,
        40.795239326802985
      ],
      [
        -73.96101025375701,
        40.79533886793717
      ],
      [
        -73.96103804978998,
        40.795389453985536
      ],
      [
        -73.96118429605254,
        40.79569901943751
      ],
      [
        -73.96119989763893,
        40.79575251000023
      ],
      [
        -73.96120970497734,
        40.79580682756678
      ],
      [
        -73.96115828249881,
        40.795839911992104
      ],
      [
        -73.96109448639125,
        40.79586580712071
      ],
      [
        -73.96102637821268,
        40.79588431973016
      ],
      [
        -73.96088417310457,
        40.79590414134477
      ],
      [
        -73.96085688645542,
        40.79594608627485
      ],
      [
        -73.96081690278983,
        40.79610774354525
      ],
      [
        -73.9607979551146,
        40.79616030394238
      ],
      [
        -73.96075747437203,
        40.79620552562796
      ],
      [
        -73.96073194823681,
        40.79624801915957
      ],
      [
        -73.96065978427912,
        40.79625260099815
      ],
      [
        -73.9606258173126,
        40.7962809577257
      ],
      [
        -73.960627,
        40.796289
      ]
    ]
  },
  {
    "name": "97 St & N T3.gpx",
    "start": [
      -73.9623,
      40.791766
    ],
    "end": [
      -73.962064,
      40.791723
    ],
    "backend": "osrm-foot/bike",
    "routeLenFt": 79.83110289756863,
    "beaconCount": 3,
    "driftFt": 2.3962973644193184,
    "angleDeg": 6,
    "maxChordFt": 60,
    "minSpacingFt": null,
    "beacons": [
      [
        -73.962296,
        40.791764
      ],
      [
        -73.96229411051792,
        40.79172902827414
      ],
      [
        -73.962088,
        40.791681
      ]
    ]
  },
  {
    "name": "97 St & N T4.gpx",
    "start": [
      -73.95804,
      40.793775
    ],
    "end": [
      -73.958126,
      40.794117
    ],
    "backend": "osrm-foot/bike",
    "routeLenFt": 127.7481533350866,
    "beaconCount": 3,
    "driftFt": 4.658416539798773,
    "angleDeg": 8,
    "maxChordFt": 60,
    "minSpacingFt": 50,
    "beacons": [
      [
        -73.958059,
        40.793778
      ],
      [
        -73.95814974147878,
        40.794036281244495
      ],
      [
        -73.958096,
        40.7941
      ]
    ]
  },
  {
    "name": "97 St & N T5.gpx",
    "start": [
      -73.95804,
      40.793775
    ],
    "end": [
      -73.958137,
      40.794091
    ],
    "backend": "osrm-foot/bike",
    "routeLenFt": 118.30469027137107,
    "beaconCount": 3,
    "driftFt": 4.658416539798773,
    "angleDeg": 8,
    "maxChordFt": 60,
    "minSpacingFt": 50,
    "beacons": [
      [
        -73.958059,
        40.793778
      ],
      [
        -73.95814974147878,
        40.794036281244495
      ],
      [
        -73.958116,
        40.794079
      ]
    ]
  },
  {
    "name": "Central Park S & N T 4.gpx",
    "start": [
      -73.975904,
      40.773765
    ],
    "end": [
      -73.974595,
      40.774616
    ],
    "backend": "osrm-foot/bike",
    "routeLenFt": 534.1283658611178,
    "beaconCount": 8,
    "driftFt": 3.8751957715440293,
    "angleDeg": 6,
    "maxChordFt": 120,
    "minSpacingFt": null,
    "beacons": [
      [
        -73.975905,
        40.773765
      ],
      [
        -73.9756852469982,
        40.774048630514365
      ],
      [
        -73.97544679679659,
        40.77432238848725
      ],
      [
        -73.97531373713727,
        40.77443927346407
      ],
      [
        -73.97532884618296,
        40.77447857690852
      ],
      [
        -73.97507456723508,
        40.77458088655298
      ],
      [
        -73.9747185189704,
        40.774627
      ],
      [
        -73.974595,
        40.774628
      ]
    ]
  },
  {
    "name": "Central Park S & N T 5.gpx",
    "start": [
      -73.973823,
      40.772807
    ],
    "end": [
      -73.973415,
      40.772757
    ],
    "backend": "osrm-foot/bike",
    "routeLenFt": 115.29192257137187,
    "beaconCount": 3,
    "driftFt": 1.419865739623813,
    "angleDeg": 1,
    "maxChordFt": 60,
    "minSpacingFt": 50,
    "beacons": [
      [
        -73.973811,
        40.772824
      ],
      [
        -73.97361339659973,
        40.77275655742195
      ],
      [
        -73.973416,
        40.772734
      ]
    ]
  },
  {
    "name": "Central Park S & N T1.gpx",
    "start": [
      -73.973072,
      40.779177
    ],
    "end": [
      -73.973587,
      40.778987
    ],
    "backend": "osrm-foot/bike",
    "routeLenFt": 691.1440631069748,
    "beaconCount": 12,
    "driftFt": 3.5616474814837256,
    "angleDeg": 4,
    "maxChordFt": 200,
    "minSpacingFt": null,
    "beacons": [
      [
        -73.973142,
        40.779137
      ],
      [
        -73.97309829409662,
        40.77909329409661
      ],
      [
        -73.97282187109174,
        40.77892158800034
      ],
      [
        -73.97275646492783,
        40.77893184192454
      ],
      [
        -73.97272487258333,
        40.77897978637037
      ],
      [
        -73.97268608139935,
        40.779193013508795
      ],
      [
        -73.97277177889774,
        40.77928092291514
      ],
      [
        -73.97292430613577,
        40.7793972070123
      ],
      [
        -73.97295892789485,
        40.77944481973714
      ],
      [
        -73.97299895195512,
        40.7795780480449
      ],
      [
        -73.97344223812473,
        40.77914808361522
      ],
      [
        -73.973575,
        40.778981
      ]
    ]
  },
  {
    "name": "Central Park S & N T2.gpx",
    "start": [
      -73.966312,
      40.77799
    ],
    "end": [
      -73.965862,
      40.777795
    ],
    "backend": "osrm-foot/bike",
    "routeLenFt": 143.61811319823897,
    "beaconCount": 4,
    "driftFt": 1.959577446038031,
    "angleDeg": 2,
    "maxChordFt": 60,
    "minSpacingFt": 30,
    "beacons": [
      [
        -73.966286,
        40.778011
      ],
      [
        -73.96617589418732,
        40.777939826094375
      ],
      [
        -73.96598018122785,
        40.77787013432506
      ],
      [
        -73.965856,
        40.777798
      ]
    ]
  },
  {
    "name": "Central Park S & N T3.gpx",
    "start": [
      -73.97157,
      40.77552
    ],
    "end": [
      -73.970368,
      40.774284
    ],
    "backend": "osrm-foot/bike",
    "routeLenFt": 740.1885021903375,
    "beaconCount": 19,
    "driftFt": 3.4481725128998595,
    "angleDeg": 8,
    "maxChordFt": 90,
    "minSpacingFt": null,
    "beacons": [
      [
        -73.971583,
        40.775513
      ],
      [
        -73.97139910694297,
        40.77534470372809
      ],
      [
        -73.97119184157575,
        40.77519156747686
      ],
      [
        -73.971129451798,
        40.77509419403758
      ],
      [
        -73.97117832291289,
        40.77487886980491
      ],
      [
        -73.971218870772,
        40.77466220294409
      ],
      [
        -73.9711792146542,
        40.77450124191589
      ],
      [
        -73.97107501533179,
        40.77436161376178
      ],
      [
        -73.97099795164031,
        40.77445278886046
      ],
      [
        -73.97093818775593,
        40.77448271204335
      ],
      [
        -73.97086968801489,
        40.77449781244279
      ],
      [
        -73.97079815588083,
        40.7744977694851
      ],
      [
        -73.97072945682754,
        40.774482792225335
      ],
      [
        -73.97066910911381,
        40.77445344482359
      ],
      [
        -73.97062170753095,
        40.77441241277979
      ],
      [
        -73.97059220564641,
        40.774362348975735
      ],
      [
        -73.97058500871726,
        40.77430781755881
      ],
      [
        -73.97052285388779,
        40.774292138357
      ],
      [
        -73.970383,
        40.77432
      ]
    ]
  }
]
